<?xml version="1.0" encoding="UTF-8"?><ROOT>
<ArchInfo Date="1622263817019" Description="version A" Name="version A" PackageName="version A.spk" UserID="sasdemo00" Version="8fee0e4">
<ContainObj>SBIP://METASERVER/GPB_Hack/prepare_data/Job_Log(Job)</ContainObj>
</ArchInfo>
<ArchInfo Date="1622264298697" Description="Log 1" Name="prepare_data" PackageName="prepare_data.spk" UserID="sasdemo00" Version="6a212a6">
<ContainObj>SBIP://METASERVER/GPB_Hack/prepare_data/prepare_data(Job)</ContainObj>
</ArchInfo>
<ArchInfo Date="1622264581978" Description="prepare_data_v1" Name="prepare_data_v1" PackageName="prepare_data_v1.spk" UserID="sasdemo00" Version="34c65f1">
<ContainObj>SBIP://METASERVER/GPB_Hack/prepare_data/prepare_data(Job)</ContainObj>
</ArchInfo>
<ArchInfo Date="1622264777998" Description="prepare_data_v2" Name="prepare_data_v2" PackageName="prepare_data_v2.spk" UserID="sasdemo00" Version="dca60a9">
<ContainObj>SBIP://METASERVER/GPB_Hack/prepare_data/prepare_data(Job)</ContainObj>
</ArchInfo>
<ArchInfo Date="1622265352856" Description="prepare_data_v3" Name="prepare_data_v3" PackageName="prepare_data_v3.spk" UserID="sasdemo00" Version="b7cf0e9">
<ContainObj>SBIP://METASERVER/GPB_Hack/prepare_data/prepare_data(Job)</ContainObj>
</ArchInfo>
</ROOT>
